hticoding/__init__.py
ithcoding-0.1.dist-info/METADATA
ithcoding-0.1.dist-info/WHEEL
ithcoding-0.1.dist-info/top_level.txt
ithcoding-0.1.dist-info/RECORD
