Metadata-Version: 2.1
Name: ithcoding
Version: 0.1
Summary: Python functions for controlling Arduino devices
Home-page: UNKNOWN
Author: hantaein
Author-email: hti7220@naver.com
License: UNKNOWN
Platform: UNKNOWN
Requires-Dist: pyserial
